odoo/addons/sale_order_whole_delivered_invoiceability/README.rst
odoo/addons/sale_order_whole_delivered_invoiceability/__init__.py
odoo/addons/sale_order_whole_delivered_invoiceability/__manifest__.py
odoo/addons/sale_order_whole_delivered_invoiceability/i18n/es.po
odoo/addons/sale_order_whole_delivered_invoiceability/i18n/it.po
odoo/addons/sale_order_whole_delivered_invoiceability/i18n/sale_order_whole_delivered_invoiceability.pot
odoo/addons/sale_order_whole_delivered_invoiceability/models/__init__.py
odoo/addons/sale_order_whole_delivered_invoiceability/models/res_partner.py
odoo/addons/sale_order_whole_delivered_invoiceability/models/sale_order.py
odoo/addons/sale_order_whole_delivered_invoiceability/readme/CONFIGURE.md
odoo/addons/sale_order_whole_delivered_invoiceability/readme/CONTRIBUTORS.md
odoo/addons/sale_order_whole_delivered_invoiceability/readme/DESCRIPTION.md
odoo/addons/sale_order_whole_delivered_invoiceability/readme/USAGE.md
odoo/addons/sale_order_whole_delivered_invoiceability/static/description/icon.png
odoo/addons/sale_order_whole_delivered_invoiceability/static/description/index.html
odoo/addons/sale_order_whole_delivered_invoiceability/tests/__init__.py
odoo/addons/sale_order_whole_delivered_invoiceability/tests/test_sale_order_whole_delivered_invoiceability.py
odoo/addons/sale_order_whole_delivered_invoiceability/views/res_partner_view.xml
odoo/addons/sale_order_whole_delivered_invoiceability/views/sale_order_view.xml
odoo_addon_sale_order_whole_delivered_invoiceability-17.0.1.0.0.4.dist-info/METADATA
odoo_addon_sale_order_whole_delivered_invoiceability-17.0.1.0.0.4.dist-info/WHEEL
odoo_addon_sale_order_whole_delivered_invoiceability-17.0.1.0.0.4.dist-info/top_level.txt
odoo_addon_sale_order_whole_delivered_invoiceability-17.0.1.0.0.4.dist-info/RECORD
